waitlyst/__init__.py
waitlyst/constants.py
waitlyst/events.py
waitlyst/exceptions.py
waitlyst/http.py
waitlyst/index.py
waitlyst/models.py
waitlyst_python-1.6.0.dist-info/METADATA
waitlyst_python-1.6.0.dist-info/WHEEL
waitlyst_python-1.6.0.dist-info/top_level.txt
waitlyst_python-1.6.0.dist-info/RECORD
