Metadata-Version: 2.1
Name: waitlyst-python
Version: 1.6.0
Summary: The easiest way to track product analytics with python.
Author-email: Waitlyst <support@waitlyst.co>
Project-URL: Homepage, https://github.com/indextrus/waitlyst-python
Keywords: analytics,tracking
Classifier: License :: OSI Approved :: MIT License
Classifier: Programming Language :: Python
Classifier: Programming Language :: Python :: 3
Requires-Python: >=2.7
Requires-Dist: requests (>=2.27.1)
Provides-Extra: dev
Requires-Dist: black ; extra == 'dev'
Requires-Dist: flake8 ; extra == 'dev'
Requires-Dist: isort ; extra == 'dev'
Requires-Dist: pip-tools ; extra == 'dev'
Requires-Dist: unittest2 ; extra == 'dev'
Requires-Dist: bumpver ; extra == 'dev'
